{
  "schema_version": 2,
  "active_work_id": "uniseek-final-fix-2361b2f7",
  "works": {
    "uniseek-final-fix-2361b2f7": {
      "work_id": "uniseek-final-fix-2361b2f7",
      "active_plan": "D:\\Temps\\yaoshi\\Desktop\\code\\istone\\AAAAAAAAAA\\UniSeek\\.omo\\plans\\uniseek-final-fix.md",
      "plan_name": "uniseek-final-fix",
      "status": "completed",
      "started_at": "2026-07-15T01:08:20.153Z",
      "updated_at": "2026-07-15T01:15:39.146Z",
      "session_ids": [
        "opencode:ses_09cccae38ffe42HCWOzXA3cQzV",
        "opencode:ses_09cae47fdffe8zG9HJfl1inUas",
        "opencode:ses_09cae3d78ffedyy6ceCMcYv5Lj",
        "opencode:ses_09cae3411ffeMj4xN3o7CKU3Gh",
        "opencode:ses_09cae2a73ffeU7PBDcESIQ5rIm",
        "opencode:ses_09cae2399ffesLrzdRZTrbFQZw",
        "opencode:ses_09cadfee9ffeBxKnXCVc4d5AOK",
        "opencode:ses_09cadebfaffeVMidCeT2w3IT7Z",
        "opencode:ses_09cade70bffeqOV7iUifw1CCQW",
        "opencode:ses_09caddcf2ffez4lTz7dMZ22h4k",
        "opencode:ses_09caaf9baffebuGlAAZi9iuptU",
        "opencode:ses_09caaec77ffe6nfM4DOG652gCt",
        "opencode:ses_09caae61cffeFS9mFBmNwcuikY",
        "opencode:ses_09caae099ffeCSpuBQ6nqdFxrD",
        "opencode:ses_09caad8cfffeCgNc2g7H9VRhGK",
        "opencode:ses_09caab042ffeSGazdlpxoIkbrx",
        "opencode:ses_09caa5678ffeAvyRHD580gyPsF",
        "opencode:ses_09caa5178ffeDDDJiADlYtMvzd",
        "opencode:ses_09caa4d62ffeFgrFf9V1UNyfIE",
        "opencode:ses_09ca8f520ffe1lvvn8bxTHo5tt",
        "opencode:ses_09ca8e73cffeKjVPKsscFJxULQ"
      ],
      "session_origins": {
        "opencode:ses_09cccae38ffe42HCWOzXA3cQzV": "direct",
        "opencode:ses_09cae47fdffe8zG9HJfl1inUas": "appended",
        "opencode:ses_09cae3d78ffedyy6ceCMcYv5Lj": "appended",
        "opencode:ses_09cae3411ffeMj4xN3o7CKU3Gh": "appended",
        "opencode:ses_09cae2a73ffeU7PBDcESIQ5rIm": "appended",
        "opencode:ses_09cae2399ffesLrzdRZTrbFQZw": "appended",
        "opencode:ses_09cadfee9ffeBxKnXCVc4d5AOK": "appended",
        "opencode:ses_09cadebfaffeVMidCeT2w3IT7Z": "appended",
        "opencode:ses_09cade70bffeqOV7iUifw1CCQW": "appended",
        "opencode:ses_09caddcf2ffez4lTz7dMZ22h4k": "appended",
        "opencode:ses_09caaf9baffebuGlAAZi9iuptU": "appended",
        "opencode:ses_09caaec77ffe6nfM4DOG652gCt": "appended",
        "opencode:ses_09caae61cffeFS9mFBmNwcuikY": "appended",
        "opencode:ses_09caae099ffeCSpuBQ6nqdFxrD": "appended",
        "opencode:ses_09caad8cfffeCgNc2g7H9VRhGK": "appended",
        "opencode:ses_09caab042ffeSGazdlpxoIkbrx": "appended",
        "opencode:ses_09caa5678ffeAvyRHD580gyPsF": "appended",
        "opencode:ses_09caa5178ffeDDDJiADlYtMvzd": "appended",
        "opencode:ses_09caa4d62ffeFgrFf9V1UNyfIE": "appended",
        "opencode:ses_09ca8f520ffe1lvvn8bxTHo5tt": "appended",
        "opencode:ses_09ca8e73cffeKjVPKsscFJxULQ": "appended"
      },
      "agent": "atlas",
      "task_sessions": {
        "todo:1": {
          "task_key": "todo:1",
          "task_label": "1",
          "task_title": "security: 创建 .gitignore + 删除废弃 SQL 文件",
          "session_id": "opencode:ses_09cae47fdffe8zG9HJfl1inUas",
          "agent": "general",
          "updated_at": "2026-07-15T01:09:40.422Z",
          "started_at": "2026-07-15T01:09:21.308Z",
          "status": "completed",
          "ended_at": "2026-07-15T01:09:40.422Z",
          "elapsed_ms": 19114
        },
        "todo:2": {
          "task_key": "todo:2",
          "task_label": "2",
          "task_title": "security: 从版本跟踪中移除含 PII 的 uniseeklv.sql",
          "session_id": "opencode:ses_09caad8cfffeCgNc2g7H9VRhGK",
          "agent": "general",
          "started_at": "2026-07-15T01:09:41.076Z",
          "status": "completed",
          "updated_at": "2026-07-15T01:14:25.974Z",
          "ended_at": "2026-07-15T01:14:25.974Z",
          "elapsed_ms": 284898
        },
        "final-wave:f1": {
          "task_key": "final-wave:f1",
          "task_label": "F1",
          "task_title": "**编译检查**: `mvn compile -f uniseek_java/pom.xml` → BUILD SUCCESS ✅",
          "session_id": "opencode:ses_09ca8e73cffeKjVPKsscFJxULQ",
          "agent": "general",
          "started_at": "2026-07-15T01:14:52.008Z",
          "status": "completed",
          "updated_at": "2026-07-15T01:15:39.146Z",
          "ended_at": "2026-07-15T01:15:39.146Z",
          "elapsed_ms": 47138
        }
      }
    }
  },
  "active_plan": "D:\\Temps\\yaoshi\\Desktop\\code\\istone\\AAAAAAAAAA\\UniSeek\\.omo\\plans\\uniseek-final-fix.md",
  "started_at": "2026-07-15T01:08:20.153Z",
  "status": "completed",\n  "updated_at": "2026-07-15T01:15:39.146Z",\n  "session_ids": [
    "opencode:ses_09cccae38ffe42HCWOzXA3cQzV",
    "opencode:ses_09cae47fdffe8zG9HJfl1inUas",
    "opencode:ses_09cae3d78ffedyy6ceCMcYv5Lj",
    "opencode:ses_09cae3411ffeMj4xN3o7CKU3Gh",
    "opencode:ses_09cae2a73ffeU7PBDcESIQ5rIm",
    "opencode:ses_09cae2399ffesLrzdRZTrbFQZw",
    "opencode:ses_09cadfee9ffeBxKnXCVc4d5AOK",
    "opencode:ses_09cadebfaffeVMidCeT2w3IT7Z",
    "opencode:ses_09cade70bffeqOV7iUifw1CCQW",
    "opencode:ses_09caddcf2ffez4lTz7dMZ22h4k",
    "opencode:ses_09caaf9baffebuGlAAZi9iuptU",
    "opencode:ses_09caaec77ffe6nfM4DOG652gCt",
    "opencode:ses_09caae61cffeFS9mFBmNwcuikY",
    "opencode:ses_09caae099ffeCSpuBQ6nqdFxrD",
    "opencode:ses_09caad8cfffeCgNc2g7H9VRhGK",
    "opencode:ses_09caab042ffeSGazdlpxoIkbrx",
    "opencode:ses_09caa5678ffeAvyRHD580gyPsF",
    "opencode:ses_09caa5178ffeDDDJiADlYtMvzd",
    "opencode:ses_09caa4d62ffeFgrFf9V1UNyfIE",
    "opencode:ses_09ca8f520ffe1lvvn8bxTHo5tt",
    "opencode:ses_09ca8e73cffeKjVPKsscFJxULQ"
  ],
  "session_origins": {
    "opencode:ses_09cccae38ffe42HCWOzXA3cQzV": "direct",
    "opencode:ses_09cae47fdffe8zG9HJfl1inUas": "appended",
    "opencode:ses_09cae3d78ffedyy6ceCMcYv5Lj": "appended",
    "opencode:ses_09cae3411ffeMj4xN3o7CKU3Gh": "appended",
    "opencode:ses_09cae2a73ffeU7PBDcESIQ5rIm": "appended",
    "opencode:ses_09cae2399ffesLrzdRZTrbFQZw": "appended",
    "opencode:ses_09cadfee9ffeBxKnXCVc4d5AOK": "appended",
    "opencode:ses_09cadebfaffeVMidCeT2w3IT7Z": "appended",
    "opencode:ses_09cade70bffeqOV7iUifw1CCQW": "appended",
    "opencode:ses_09caddcf2ffez4lTz7dMZ22h4k": "appended",
    "opencode:ses_09caaf9baffebuGlAAZi9iuptU": "appended",
    "opencode:ses_09caaec77ffe6nfM4DOG652gCt": "appended",
    "opencode:ses_09caae61cffeFS9mFBmNwcuikY": "appended",
    "opencode:ses_09caae099ffeCSpuBQ6nqdFxrD": "appended",
    "opencode:ses_09caad8cfffeCgNc2g7H9VRhGK": "appended",
    "opencode:ses_09caab042ffeSGazdlpxoIkbrx": "appended",
    "opencode:ses_09caa5678ffeAvyRHD580gyPsF": "appended",
    "opencode:ses_09caa5178ffeDDDJiADlYtMvzd": "appended",
    "opencode:ses_09caa4d62ffeFgrFf9V1UNyfIE": "appended",
    "opencode:ses_09ca8f520ffe1lvvn8bxTHo5tt": "appended",
    "opencode:ses_09ca8e73cffeKjVPKsscFJxULQ": "appended"
  },
  "plan_name": "uniseek-final-fix",
  "task_sessions": {
    "todo:1": {
      "task_key": "todo:1",
      "task_label": "1",
      "task_title": "security: 创建 .gitignore + 删除废弃 SQL 文件",
      "session_id": "opencode:ses_09cae47fdffe8zG9HJfl1inUas",
      "agent": "general",
      "updated_at": "2026-07-15T01:09:40.422Z",
      "started_at": "2026-07-15T01:09:21.308Z",
      "status": "completed",
      "ended_at": "2026-07-15T01:09:40.422Z",
      "elapsed_ms": 19114
    },
    "todo:2": {
      "task_key": "todo:2",
      "task_label": "2",
      "task_title": "security: 从版本跟踪中移除含 PII 的 uniseeklv.sql",
      "session_id": "opencode:ses_09caad8cfffeCgNc2g7H9VRhGK",
      "agent": "general",
      "started_at": "2026-07-15T01:09:41.076Z",
      "status": "completed",
      "updated_at": "2026-07-15T01:14:25.974Z",
      "ended_at": "2026-07-15T01:14:25.974Z",
      "elapsed_ms": 284898
    },
    "final-wave:f1": {
      "task_key": "final-wave:f1",
      "task_label": "F1",
      "task_title": "**编译检查**: `mvn compile -f uniseek_java/pom.xml` → BUILD SUCCESS ✅",
      "session_id": "opencode:ses_09ca8e73cffeKjVPKsscFJxULQ",
      "agent": "general",
      "started_at": "2026-07-15T01:14:52.008Z",
      "status": "completed",
      "updated_at": "2026-07-15T01:15:39.146Z",
      "ended_at": "2026-07-15T01:15:39.146Z",
      "elapsed_ms": 47138
    }
  },
  "agent": "atlas"
}